{"xlv":{"w":"xlv","en":[{"p":"adjective","d":"the Roman numeral for 45","e":""}]},"x-linked":{"w":"X-linked","en":[{"p":"adjective","d":"relating to genes or characteristics or conditions carried on the X chromosome","e":"I think it might be an X-linked mutation."}]},"xerography":{"w":"xerography","en":[{"p":"noun","d":"forming an image by the action of light on a specially coated charged plate","e":"The machine used xerography to print copies."}]},"xanthemia":{"w":"xanthemia","en":[{"p":"noun","d":"excess carotene in the blood stream","e":"Eating too many carrots had contributed to the child's xanthemia."}]},"xii":{"w":"xii","en":[{"p":"adjective","d":"the Roman numeral for 12","e":""}]},"xerostomia":{"w":"xerostomia","en":[{"p":"noun","d":"abnormal dryness of the mouth resulting from decreased secretion of saliva","e":""}]},"xerophile":{"w":"xerophile","en":[{"p":"noun","d":"plant adapted for life with a limited supply of water","e":"Cacti are some of the most well-known xerophiles."}]},"xanthophyll":{"w":"xanthophyll","en":[{"p":"noun","d":"yellow carotenoid pigments in plants and animal fats and egg yolks","e":""}],"vi":[{"pos":"Danh từ","means":["(thực vật học) xantofin"],"ex":[]}]},"xci":{"w":"xci","en":[{"p":"adjective","d":"the Roman numeral for 91","e":""}]},"xanthophyl":{"w":"xanthophyl","en":[{"p":"noun","d":"yellow carotenoid pigments in plants and animal fats and egg yolks","e":""}]},"x-axis":{"w":"x-axis","en":[{"p":"noun","d":"the horizontal axis in a plane coordinate system","e":"We marked the x-axis with the number of visitors that the museum received."}],"vi":[{"pos":"Danh từ","means":["(toán học) trục hoành"],"ex":[]}]},"xxxvi":{"w":"xxxvi","en":[{"p":"adjective","d":"the Roman numeral for 36","e":""}]},"xlii":{"w":"xlii","en":[{"p":"adjective","d":"the Roman numeral for 42","e":""}]},"xenotransplantation":{"w":"xenotransplantation","en":[{"p":"noun","d":"a surgical procedure in which tissue or whole organs are transfered from one species to another species","e":"The comparable sizes of organs in pigs and humans means that xenotransplantation could be feasible."}]},"xxix":{"w":"xxix","en":[{"p":"adjective","d":"the Roman numeral for 29","e":""}]},"xv":{"w":"xv","en":[{"p":"adjective","d":"the Roman numeral for 15","e":""}]},"xxvi":{"w":"xxvi","en":[{"p":"adjective","d":"the Roman numeral for 26","e":""}]},"xeroxed":{"w":"xeroxed","ipa":"/ˈzɪɹɑkst/","vi":[{"pos":"Danh từ","means":["phương pháp sao chụp khô"],"ex":[{"en":"a Xerox machine","vi":"máy sao chụp khô"}]},{"pos":"Động từ","means":["sao chụp khô"],"ex":[{"en":"could you xerox this letter please, Paula?","vi":"Paula làm ơn sao chụp hộ cái thư này, được không?"}]}]},"xanthine":{"w":"xanthine","en":[{"p":"noun","d":"crystalline oxidation product of the metabolism of nucleoproteins","e":"Once generated from guanine, xanthine is often turned into uric acid."}],"vi":[{"pos":"Danh từ","means":["(hoá học) xantin"],"ex":[]}]},"xlvii":{"w":"xlvii","en":[{"p":"adjective","d":"the Roman numeral for 47","e":""}]},"xxi":{"w":"xxi","en":[{"p":"adjective","d":"the Roman numeral for 21","e":""}]},"xix":{"w":"xix","en":[{"p":"adjective","d":"the Roman numeral for 19","e":""}]},"xanthopsia":{"w":"xanthopsia","en":[{"p":"noun","d":"visual defect in which objects appear to have a yellowish hue","e":"The drug digitalin is thought to cause xanthopsia."}]},"xanthelasma":{"w":"xanthelasma","en":[{"p":"noun","d":"xanthoma of the eyelids","e":""}]},"xcvii":{"w":"xcvii","en":[{"p":"adjective","d":"the number 97 in Roman numerals","e":"It's my xcvii birthday, Augustus!"}]},"xeroxing":{"w":"xeroxing","ipa":"/ˈzɪɹɑksɪŋ/","vi":[{"pos":"Danh từ","means":["phương pháp sao chụp khô"],"ex":[{"en":"a Xerox machine","vi":"máy sao chụp khô"}]},{"pos":"Động từ","means":["sao chụp khô"],"ex":[{"en":"could you xerox this letter please, Paula?","vi":"Paula làm ơn sao chụp hộ cái thư này, được không?"}]}]},"xciv":{"w":"xciv","en":[{"p":"adjective","d":"nintey-four in Roman numerals","e":""}]},"xi":{"w":"xi","ipa":"/ˈʃi/","en":[{"p":"adjective","d":"the Roman numeral for 11","e":""},{"p":"noun","d":"the 14th letter of the Greek alphabet","e":""}],"vi":[{"pos":"","means":["ski (&amp;"],"ex":[]}]},"xenograft":{"w":"xenograft","en":[{"p":"noun","d":"tissue from an animal of one species used as a temporary graft, as in cases of severe burns, on an individual of another species","e":"The surgeons used skin from a pig as a xenograft."}]},"xenotransplant":{"w":"xenotransplant","en":[{"p":"noun","d":"a surgical procedure in which tissue or whole organs are transfered from one species to another species","e":""}]},"xcviii":{"w":"xcviii","en":[{"p":"adjective","d":"the Roman numeral for 98","e":""}]},"xanthomonad":{"w":"xanthomonad","en":[{"p":"noun","d":"bacteria producing yellow non-water-soluble pigments","e":"I cultured a flask full of xanthomonad."}]},"xciii":{"w":"xciii","en":[{"p":"adjective","d":"the Roman numeral for 93","e":""}]},"xx":{"w":"xx","en":[{"p":"adjective","d":"the Roman numeral for 20","e":""}],"vi":[{"pos":"Danh từ","means":["(từ Mỹ) tờ 20 đô la","(viết tắt) của double-cross (từ lóng) sự lừa dối; sự phản bội"],"ex":[{"en":"I know you gave me the XX","vi":"Tôi biết rằng anh đã phản bội lại tôi"}]}]},"xcl":{"w":"xcl","en":[{"p":"adjective","d":"the Roman numeral for 190","e":""}]},"xerophthalmia":{"w":"xerophthalmia","en":[{"p":"noun","d":"abnormal dryness of the conjunctiva and cornea of the eyes","e":""}],"vi":[{"pos":"Danh từ","means":["(y học) bệnh khô mắt"],"ex":[]}]},"xxxviii":{"w":"xxxviii","en":[{"p":"adjective","d":"the Roman numeral for 38","e":""}]},"xeroxes":{"w":"xeroxes","ipa":"/ˈzɪɹɑksɪz/","vi":[{"pos":"Danh từ","means":["phương pháp sao chụp khô"],"ex":[{"en":"a Xerox machine","vi":"máy sao chụp khô"}]},{"pos":"Động từ","means":["sao chụp khô"],"ex":[{"en":"could you xerox this letter please, Paula?","vi":"Paula làm ơn sao chụp hộ cái thư này, được không?"}]}]},"xliv":{"w":"xliv","en":[{"p":"adjective","d":"the Roman numeral for 44","e":""}]},"xeroma":{"w":"xeroma","en":[{"p":"noun","d":"abnormal dryness of the conjunctiva and cornea of the eyes","e":"Your eyes have a condition called xeroma."}]},"xylophonist":{"w":"xylophonist","en":[{"p":"noun","d":"someone who plays a xylophone","e":"The xylophonist played the Danse Macabre."}]},"xanthoma":{"w":"xanthoma","en":[{"p":"noun","d":"a skin problem marked by the development of irregular yellow nodules on the eyelids, neck and back","e":"The patient is suffering from xanthoma."}]},"xl":{"w":"xl","en":[{"p":"adjective","d":"the Roman numeral for 40","e":""}],"vi":[{"pos":"","means":["quá rộng (extra large)"],"ex":[]}]},"xiii":{"w":"xiii","en":[{"p":"adjective","d":"the Roman numeral for 13","e":""}]},"xxxv":{"w":"xxxv","en":[{"p":"adjective","d":"the Roman numeral for 35","e":""}]},"xenon":{"w":"xenon","ipa":"/ˈzinɑn/","en":[{"p":"noun","d":"a colorless, odorless, inert gaseous element occurring in the earth's atmosphere in trace amounts","e":"The canister was filled with xenon."}],"vi":[{"pos":"Danh từ","means":["xenon"],"ex":[]}]},"xxxiii":{"w":"xxxiii","en":[{"p":"adjective","d":"the Roman numeral for 33","e":""}]},"xviii":{"w":"xviii","en":[{"p":"adjective","d":"the Roman numeral for 18","e":""}]},"xerographic":{"w":"xerographic","en":[{"p":"adjective","d":"of or relating to copying paper or other items, aka xerography","e":"Our xerographic machine was on the fritz."}]},"x-raying":{"w":"X-raying","en":[{"p":"noun","d":"obtaining images by the use of X rays","e":"The pictures from the X-raying were analyzed by the dentist."}]},"xeroradiography":{"w":"xeroradiography","en":[{"p":"noun","d":"radiography using X-rays and xerographic techniques","e":"The radiologist specialized in xeroradiography."}]},"xcvi":{"w":"xcvi","en":[{"p":"adjective","d":"the Roman numeral for 96","e":""}]},"xcv":{"w":"xcv","en":[{"p":"adjective","d":"the Roman numeral for 95","e":""}]},"xenogeneic":{"w":"xenogeneic","en":[{"p":"adjective","d":"denoting or relating to cells or tissues from individuals belonging to different species","e":"The xenogenic reactions of trees and mosses is quite fascinating."}]},"xenophobia":{"w":"xenophobia","ipa":"/ˌzɛnəˈfoʊbiə/","en":[{"p":"noun","d":"a fear of foreigners or strangers","e":"I think your xenophobia might be cured by a trip abroad."}],"vi":[{"pos":"Danh từ","means":["sự bài ngoại"],"ex":[]}]},"xxxiv":{"w":"xxxiv","en":[{"p":"adjective","d":"the Roman numeral for 34","e":""}]},"xylene":{"w":"xylene","en":[{"p":"noun","d":"a colorless flammable volatile liquid hydrocarbon used as a solvent","e":""}]},"xeroderma":{"w":"xeroderma","en":[{"p":"noun","d":"a mild form of ichthyosis characterized by abnormal dryness and roughness of the skin","e":""}]},"xxx":{"w":"xxx","en":[{"p":"adjective","d":"the Roman numeral for 30","e":""}]},"xiv":{"w":"xiv","en":[{"p":"adjective","d":"the Roman numeral for 14","e":""}]},"xliii":{"w":"xliii","en":[{"p":"adjective","d":"the Roman numeral for 43","e":""}]},"x-ray":{"w":"x-ray","ipa":"/ˈɛksˌɹeɪ/","en":[{"p":"verb","d":"take an x-ray of something or somebody","e":"The doctor x-rayed my chest"},{"p":"verb","d":"examine by taking x-rays","e":""}],"vi":[{"pos":"Danh từ","means":["(thường số nhiều) tia X, X quang","ảnh X quang","(khẩu ngữ) sự soi X quang"],"ex":[]},{"pos":"Động từ","means":["soi X quang","chụp X quang","điều trị bằng X quang"],"ex":[]}]},"xerophthalmus":{"w":"xerophthalmus","en":[{"p":"noun","d":"abnormal dryness of the conjunctiva and cornea of the eyes","e":""}]},"xylose":{"w":"xylose","en":[{"p":"noun","d":"a sugar extracted from wood or straw","e":"Xylose is found in most plants that humans consume."}]},"xxxi":{"w":"xxxi","en":[{"p":"adjective","d":"thirty-one in Roman numerals","e":""}]},"xylol":{"w":"xylol","en":[{"p":"noun","d":"a colorless flammable volatile liquid hydrocarbon used as a solvent","e":"The only way the powder would dissolve was in xylol."}]},"xerox":{"w":"xerox","ipa":"/ˈzɪɹɑks/","en":[{"p":"noun","d":"a copy made by a xerographic printer","e":""},{"p":"verb","d":"reproduce by xerography","e":""}],"vi":[{"pos":"Danh từ","means":["phương pháp sao chụp khô"],"ex":[{"en":"a Xerox machine","vi":"máy sao chụp khô"}]},{"pos":"Động từ","means":["sao chụp khô"],"ex":[{"en":"could you xerox this letter please, Paula?","vi":"Paula làm ơn sao chụp hộ cái thư này, được không?"}]}]},"xebec":{"w":"xebec","ipa":"/ˈzɛbək/","vi":[{"pos":"Danh từ","means":["(hàng hải) thuyền xêbec, thuyền ba cột buồm (ở Địa trung hải)"],"ex":[]}]},"xanthous":{"w":"xanthous","en":[{"p":"adjective","d":"of the color intermediate between green and orange in the color spectrum","e":"The new rug you bought is fairly xanthous, don't you think?"}],"vi":[{"pos":"Tính từ","means":["(nhân chủng học) vàng (da)"],"ex":[]}]},"xylophone":{"w":"xylophone","ipa":"/ˈzaɪɫəˌfoʊn/","en":[{"p":"noun","d":"a percussion instrument with wooden bars tuned to produce a chromatic scale, with resonators to help with the sound quality","e":"The children were encouraged to play the xylophone."}],"vi":[{"pos":"Danh từ","means":["mộc cầm"],"ex":[]}]},"xanthate":{"w":"xanthate","en":[{"p":"noun","d":"a salt or ester of xanthic acid","e":""}],"vi":[{"pos":"Danh từ","means":["(hoá học) xantat"],"ex":[]}]},"xerotes":{"w":"xerotes","en":[{"p":"noun","d":"the condition of not containing or being covered by a liquid, especially water","e":"The xerotes of the skin was helped by applying a wax."}]},"xxvii":{"w":"xxvii","en":[{"p":"adjective","d":"being seven more than twenty","e":""}]},"xenophobic":{"w":"xenophobic","ipa":"/ˌzɛnəˈfɑbɪk/","en":[{"p":"adjective","d":"suffering from xenophobia, or the fear of outsiders","e":"Those remarks make it pretty clear how xenophobic you are."}],"vi":[{"pos":"Tính từ","means":["bài ngoại"],"ex":[]}]},"xxiii":{"w":"xxiii","en":[{"p":"adjective","d":"the Roman numeral for 23","e":""}]},"xxxii":{"w":"xxxii","en":[{"p":"adjective","d":"the Roman numeral for 32","e":""}]},"xenogenesis":{"w":"xenogenesis","en":[{"p":"noun","d":"the production of offspring that is distinct from either parent","e":"The two creatures did not look alike, but were thought to be different stages in xenogenesis."}]},"xeric":{"w":"xeric","en":[{"p":"adjective","d":"being deficient in moisture","e":"The Sahara desert is a xeric environment – it rarely rains there."}]},"x-rays":{"w":"x-rays","ipa":"/ˈɛksˌɹeɪz/","vi":[{"pos":"","means":["tia x, tia rơn ghen"],"ex":[]}]},"xenotime":{"w":"xenotime","en":[{"p":"noun","d":"a brown-to-yellow mineral that is a phosphate of yttrium in crystalline form","e":""}]},"xvii":{"w":"xvii","en":[{"p":"adjective","d":"the Roman numeral for 17","e":""}]},"xxiv":{"w":"xxiv","en":[{"p":"adjective","d":"the Roman numeral for 24","e":""}]},"xenolith":{"w":"xenolith","en":[{"p":"noun","d":"a piece of rock of different origin from the igneous rock in which it is embedded","e":""}]},"xanthomatosis":{"w":"xanthomatosis","en":[{"p":"noun","d":"widespread xanthomas (especially on elbows and knees)","e":""}]},"xerophyte":{"w":"xerophyte","en":[{"p":"noun","d":"plant adapted for life with a limited supply of water","e":"The gardener loved the easy maintenance of the xerophyte."}],"vi":[{"pos":"Danh từ","means":["(thực vật học) cây ưa khô, cây chịu hạn"],"ex":[]}]},"xlviii":{"w":"xlviii","en":[{"p":"adjective","d":"the Roman numeral for 48","e":""}]},"x":{"w":"x","ipa":"/ˈɛks/","en":[{"p":"adjective","d":"the Roman numeral for 10","e":""},{"p":"noun","d":"the 24th letter of the Roman alphabet","e":"The farmer signed with an x."}],"vi":[{"pos":"Danh từ","means":["X, x","(ký hiệu, chữ số La Mã) 10","(toán học) x,ẩn số x","người nào đó; ông X; bà X","dấu đánh dấu (trên bản đồ…)","Christ (Xtian = Christian; Xmas = Christmas)"],"ex":[{"en":"\"Xylophone\" begins with [an] X","vi":"\"Xylophone\" bắt đầu bằng con chữ X"},{"en":"Mr and Mrs X","vi":"ông bà X"}]}]},"xylem":{"w":"xylem","en":[{"p":"noun","d":"the woody part of plants: the supporting and water-conducting tissue, consisting primarily of tracheids and vessels","e":"The xylem carries water up into the tree."}],"vi":[{"pos":"Danh từ","means":["(thực vật học) chất gỗ, xylem"],"ex":[]}]},"xxii":{"w":"xxii","en":[{"p":"adjective","d":"the Roman numeral for 22","e":""}]},"xanthosis":{"w":"xanthosis","en":[{"p":"noun","d":"an abnormal yellow discoloration of the skin","e":"The child was so unhealthy that the skin displayed xanthosis."}]},"xc":{"w":"xc","en":[{"p":"adjective","d":"the Roman numeral for 90","e":""}]},"xerodermia":{"w":"xerodermia","en":[{"p":"noun","d":"a mild form of ichthyosis characterized by abnormal dryness and roughness of the skin","e":""}]},"xerophytic":{"w":"xerophytic","en":[{"p":"adjective","d":"adapted to a dry environment","e":"Cacti are xerophytic plants."}]},"xxviii":{"w":"xxviii","en":[{"p":"adjective","d":"the Roman numeral for 28","e":""}]},"xvi":{"w":"xvi","en":[{"p":"adjective","d":"the Roman numeral for 16","e":""}]},"xxxvii":{"w":"xxxvii","en":[{"p":"adjective","d":"the Roman numeral for 37","e":""}]},"xlvi":{"w":"xlvi","en":[{"p":"adjective","d":"the Roman numeral for 46","e":""}]},"xxv":{"w":"xxv","en":[{"p":"adjective","d":"the Roman numeral for 25","e":""}]}}